samdasootest/test1.py
samdasootest/test2.py
samdasootest-0.0.0.1.dist-info/METADATA
samdasootest-0.0.0.1.dist-info/WHEEL
samdasootest-0.0.0.1.dist-info/top_level.txt
samdasootest-0.0.0.1.dist-info/RECORD
