Metadata-Version: 2.1
Name: samdasootest
Version: 0.0.0.1
Summary: My First Test Package
Home-page: https://lingua.blog.me/...
Author: hajun
Author-email: jhajun1026@naver.com
License: MIT
Requires-Python: >=3
